uniparser_udmurt/__init__.py
uniparser_udmurt/data_nodiacritics/__init__.py
uniparser_udmurt/data_nodiacritics/bad_analyses.txt
uniparser_udmurt/data_nodiacritics/lex_rules.txt
uniparser_udmurt/data_nodiacritics/lexemes.txt
uniparser_udmurt/data_nodiacritics/paradigms.txt
uniparser_udmurt/data_nodiacritics/udmurt_disambiguation.cg3
uniparser_udmurt/data_oldorth/__init__.py
uniparser_udmurt/data_oldorth/bad_analyses.txt
uniparser_udmurt/data_oldorth/lex_rules.txt
uniparser_udmurt/data_oldorth/lexemes.txt
uniparser_udmurt/data_oldorth/paradigms.txt
uniparser_udmurt/data_oldorth/udmurt_disambiguation.cg3
uniparser_udmurt/data_strict/__init__.py
uniparser_udmurt/data_strict/bad_analyses.txt
uniparser_udmurt/data_strict/lex_rules.txt
uniparser_udmurt/data_strict/lexemes.txt
uniparser_udmurt/data_strict/paradigms.txt
uniparser_udmurt/data_strict/udmurt_disambiguation.cg3
uniparser_udmurt-2.2.3.dist-info/LICENSE
uniparser_udmurt-2.2.3.dist-info/METADATA
uniparser_udmurt-2.2.3.dist-info/WHEEL
uniparser_udmurt-2.2.3.dist-info/top_level.txt
uniparser_udmurt-2.2.3.dist-info/RECORD
